gsql2rsql/__init__.py
gsql2rsql/cli.py
gsql2rsql/graph_context.py
gsql2rsql/pyspark_executor.py
gsql2rsql/common/__init__.py
gsql2rsql/common/exceptions.py
gsql2rsql/common/logging.py
gsql2rsql/common/schema.py
gsql2rsql/common/utils.py
gsql2rsql/parser/__init__.py
gsql2rsql/parser/ast.py
gsql2rsql/parser/opencypher_parser.py
gsql2rsql/parser/operators.py
gsql2rsql/parser/visitor.py
gsql2rsql/parser/grammar/Cypher.g4
gsql2rsql/parser/grammar/Cypher.interp
gsql2rsql/parser/grammar/Cypher.tokens
gsql2rsql/parser/grammar/CypherLexer.interp
gsql2rsql/parser/grammar/CypherLexer.py
gsql2rsql/parser/grammar/CypherLexer.tokens
gsql2rsql/parser/grammar/CypherListener.py
gsql2rsql/parser/grammar/CypherParser.py
gsql2rsql/parser/grammar/CypherVisitor.py
gsql2rsql/parser/grammar/__init__.py
gsql2rsql/planner/__init__.py
gsql2rsql/planner/aggregation_boundary.py
gsql2rsql/planner/bidirectional_optimizer.py
gsql2rsql/planner/column_ref.py
gsql2rsql/planner/column_resolver.py
gsql2rsql/planner/data_types.py
gsql2rsql/planner/dead_table_eliminator.py
gsql2rsql/planner/logical_plan.py
gsql2rsql/planner/match_tree.py
gsql2rsql/planner/operators.py
gsql2rsql/planner/path_analyzer.py
gsql2rsql/planner/recursive_traversal.py
gsql2rsql/planner/schema.py
gsql2rsql/planner/subquery_optimizer.py
gsql2rsql/planner/symbol_table.py
gsql2rsql/renderer/__init__.py
gsql2rsql/renderer/schema_provider.py
gsql2rsql/renderer/sql_renderer.py
gsql2rsql-0.8.2.dist-info/METADATA
gsql2rsql-0.8.2.dist-info/WHEEL
gsql2rsql-0.8.2.dist-info/entry_points.txt
gsql2rsql-0.8.2.dist-info/RECORD
