Metadata-Version: 2.4
Name: gsql2rsql
Version: 0.8.2
Summary: Transpile Graph Query Language (openCypher) to Recursive SQL (Databricks)
Author-email: Bruno Messias <devmessias@gmail.com>
License: MIT
Keywords: cypher,databricks,graph,opencypher,query,recursive,sql,transpiler
Classifier: Development Status :: 3 - Alpha
Classifier: Intended Audience :: Developers
Classifier: License :: OSI Approved :: MIT License
Classifier: Programming Language :: Python :: 3
Classifier: Programming Language :: Python :: 3.12
Classifier: Programming Language :: Python :: 3.13
Classifier: Topic :: Database
Classifier: Topic :: Software Development :: Compilers
Classifier: Typing :: Typed
Requires-Python: >=3.11
Requires-Dist: antlr4-python3-runtime>=4.13.0
Requires-Dist: click>=8.1.0
Requires-Dist: colorama>=0.4.6
Requires-Dist: prompt-toolkit>=3.0.0
Requires-Dist: pyyaml>=6.0
Requires-Dist: rich>=13.0.0
Requires-Dist: textual>=0.47.0
Provides-Extra: dev
Requires-Dist: mypy>=1.8.0; extra == 'dev'
Requires-Dist: pyright>=1.1.0; extra == 'dev'
Requires-Dist: pyspark>=3.5.0; extra == 'dev'
Requires-Dist: pytest-cov>=4.1.0; extra == 'dev'
Requires-Dist: pytest-timeout>=2.1.0; extra == 'dev'
Requires-Dist: pytest>=8.0.0; extra == 'dev'
Requires-Dist: ruff>=0.2.0; extra == 'dev'
